secret_generator/__init__.py
secret_generator/cli_helper.py
secret_generator/config.py
secret_generator/generate_htpasswd.py
secret_generator/generate_secret.py
secret_generator/operators_helper.py
secret_generator-0.2.1.dist-info/LICENSE
secret_generator-0.2.1.dist-info/METADATA
secret_generator-0.2.1.dist-info/WHEEL
secret_generator-0.2.1.dist-info/RECORD
