Metadata-Version: 2.3
Name: secret_generator
Version: 0.2.1
Summary: 
License: Apache-2.0
Author: Bakminstof
Author-email: bakminstof@yandex.ru
Requires-Python: >=3.12,<4.0
Classifier: License :: OSI Approved :: Apache Software License
Classifier: Programming Language :: Python :: 3
Classifier: Programming Language :: Python :: 3.12
Classifier: Programming Language :: Python :: 3.13
Requires-Dist: bcrypt (>=4.3.0,<5.0.0)
Project-URL: Repository, https://github.com/Bakminstof/secret_generator
